ffmpeg_2pass_tools/__init__.py
ffmpeg_2pass_tools/burst_shots_into_live_photo.py
ffmpeg_2pass_tools/burst_shots_into_live_photo_test.py
ffmpeg_2pass_tools/exiftool_utils.py
ffmpeg_2pass_tools/ffmpeg_2pass_and_exif.py
ffmpeg_2pass_tools/get_ffmpeg_input_flags.py
ffmpeg_2pass_tools/get_ffmpeg_input_flags_test.py
ffmpeg_2pass_tools/highlight.py
ffmpeg_2pass_tools/image_file.py
ffmpeg_2pass_tools/image_file_test.py
ffmpeg_2pass_tools/third_party/__init__.py
ffmpeg_2pass_tools/third_party/MotionPhoto2/.git
ffmpeg_2pass_tools/third_party/MotionPhoto2/.gitignore
ffmpeg_2pass_tools/third_party/MotionPhoto2/LICENSE
ffmpeg_2pass_tools/third_party/MotionPhoto2/Muxer.py
ffmpeg_2pass_tools/third_party/MotionPhoto2/README.md
ffmpeg_2pass_tools/third_party/MotionPhoto2/SamsungTags.py
ffmpeg_2pass_tools/third_party/MotionPhoto2/constants.py
ffmpeg_2pass_tools/third_party/MotionPhoto2/motionphoto2
ffmpeg_2pass_tools/third_party/MotionPhoto2/motionphoto2.py
ffmpeg_2pass_tools/third_party/MotionPhoto2/requirements.txt
ffmpeg_2pass_tools/third_party/MotionPhoto2/utils.py
ffmpeg_2pass_tools/third_party/MotionPhoto2/documentation/images/GUI.png
ffmpeg_2pass_tools/third_party/MotionPhoto2/legacy_ps1/.gitignore
ffmpeg_2pass_tools/third_party/MotionPhoto2/legacy_ps1/MotionPhoto2.cmd
ffmpeg_2pass_tools/third_party/MotionPhoto2/legacy_ps1/MotionPhoto2.ps1
ffmpeg_2pass_tools/third_party/MotionPhoto2/legacy_ps1/README.md
ffmpeg_2pass_tools-0.1.2.dist-info/METADATA
ffmpeg_2pass_tools-0.1.2.dist-info/WHEEL
ffmpeg_2pass_tools-0.1.2.dist-info/entry_points.txt
ffmpeg_2pass_tools-0.1.2.dist-info/licenses/LICENSE
ffmpeg_2pass_tools-0.1.2.dist-info/RECORD
