Metadata-Version: 2.4
Name: ffmpeg-2pass-tools
Version: 0.1.2
Summary: A collection of tools for working with FFmpeg, including two-pass encoding and EXIF data handling
Author-email: YoungCatChen <YoungCatChen@users.noreply.github.com>
License-Expression: MIT
License-File: LICENSE
Requires-Python: >=3.7
Requires-Dist: gooey
Requires-Dist: lxml
Requires-Dist: pyexiftool
Provides-Extra: test
Requires-Dist: parameterized; extra == 'test'
